protego/__init__.py
protego/datasets/delivered/sqli_test.csv
protego/datasets/delivered/sqli_train.csv
protego/models/__init__.py
protego/models/base.py
protego/models/batch.py
protego/models/online.py
protego/models/types.py
protego/pretrained/decision_tree_knnb.pkl
protego/pretrained/decision_tree_knno.pkl
protego/pretrained/decision_tree_logb.pkl
protego/pretrained/decision_tree_logo.pkl
protego/pretrained/decision_tree_mnbb.pkl
protego/pretrained/decision_tree_mnbo.pkl
protego/pretrained/decision_tree_perb.pkl
protego/pretrained/decision_tree_pero.pkl
protego/pretrained/decision_tree_ranb.pkl
protego/pretrained/decision_tree_rano.pkl
protego/pretrained/decision_tree_treb.pkl
protego/pretrained/decision_tree_treo.pkl
protego/utils/__init__.py
protego/utils/data_loader.py
protego/utils/feature_extractor.py
protego/utils/types.py
protego_sqli-1.0.1.dist-info/LICENSE
protego_sqli-1.0.1.dist-info/METADATA
protego_sqli-1.0.1.dist-info/WHEEL
protego_sqli-1.0.1.dist-info/top_level.txt
protego_sqli-1.0.1.dist-info/RECORD
