Metadata-Version: 2.1
Name: protego-sqli
Version: 1.0.1
Summary: Detect SQL Injection Payloads
Home-page: https://github.com/reevesba/protego
Author: Bradley Reeves
Author-email: reevesbra@outlook.com
License: UNKNOWN
Platform: UNKNOWN
Classifier: Programming Language :: Python :: 3
Classifier: License :: OSI Approved :: MIT License
Classifier: Operating System :: OS Independent
Requires-Python: >=3.9
License-File: LICENSE
Requires-Dist: pandas (==1.4.2)
Requires-Dist: numpy (==1.22.3)
Requires-Dist: river (==0.10.1)
Requires-Dist: scikit-learn (==1.0.2)
